maatpy/__init__.py
maatpy/alias.py
maatpy/atoms.py
maatpy/classes.py
maatpy/constants.py
maatpy/deuteration.py
maatpy/elements.py
maatpy/fit.py
maatpy/normalize.py
maatpy/plot.py
maatpy/sample.py
maatpy-3.1.1.dist-info/LICENSE
maatpy-3.1.1.dist-info/METADATA
maatpy-3.1.1.dist-info/WHEEL
maatpy-3.1.1.dist-info/top_level.txt
maatpy-3.1.1.dist-info/RECORD
