Metadata-Version: 2.1
Name: maatpy
Version: 3.1.1
Summary: The spectruM AnAlysis Tools for Python, or MaatPy, is a Python package to analyze scientific data, with a special focus in spectral data from INS, FTIR and Raman, among others.
Author: Pablo Gila-Herranz
Author-email: pgila001@ikasle.ehu.eus
License: AGPL-3.0
Keywords: python,Maat,MaatPy,Inelastic Neutron Scattering,INS,Raman,ATR,FTIR,spectroscopy,spectra,analysis
Classifier: Development Status :: 5 - Production/Stable
Classifier: Natural Language :: English
Classifier: Intended Audience :: Science/Research
Classifier: Programming Language :: Python :: 3
Classifier: Operating System :: POSIX :: Linux
Classifier: Operating System :: Microsoft :: Windows
Classifier: Operating System :: Other OS
Requires-Python: >=3
License-File: LICENSE
Requires-Dist: numpy
Requires-Dist: matplotlib
Requires-Dist: pandas
Requires-Dist: scipy
